pawdbt/__init__.py
pawdbt/pawdbt.py
pawdbt/pawdbt_helper_modules.py
pawdbt-1.1.0.dist-info/LICENSE
pawdbt-1.1.0.dist-info/METADATA
pawdbt-1.1.0.dist-info/WHEEL
pawdbt-1.1.0.dist-info/entry_points.txt
pawdbt-1.1.0.dist-info/top_level.txt
pawdbt-1.1.0.dist-info/RECORD
