Metadata-Version: 2.1
Name: pawdbt
Version: 1.1.0
Summary: Bespoke automation for documenting dbt models
Home-page: https://github.com/dan-wils0n/pawdbt
Author: Dan Wilson
Author-email: dan@dans.design
License: MIT
Platform: UNKNOWN
Classifier: Development Status :: 3 - Alpha
Classifier: License :: OSI Approved :: MIT License
Classifier: Programming Language :: Python :: 3
Classifier: Programming Language :: Python :: 3.6
Classifier: Programming Language :: Python :: 3.7
Classifier: Programming Language :: Python :: 3.8
Classifier: Programming Language :: Python :: 3.9
License-File: LICENSE
Requires-Dist: argparse
Requires-Dist: tqdm
Requires-Dist: prettytable
Requires-Dist: halo
